victor_pecas/__init__.py
victor_pecas/__version__.py
victor_pecas/tfidf_vectorizer.py
victor_pecas/victor_pieces.py
victor_pecas-0.1.0.dev3.dist-info/LICENSE
victor_pecas-0.1.0.dev3.dist-info/METADATA
victor_pecas-0.1.0.dev3.dist-info/WHEEL
victor_pecas-0.1.0.dev3.dist-info/top_level.txt
victor_pecas-0.1.0.dev3.dist-info/RECORD
