Metadata-Version: 2.1
Name: victor-pecas
Version: 0.1.0.dev3
Summary: GPAM Victor Pecas
Home-page: https://gitlab.com/gpam/victor/SERVICES/victor-pecas
Author: GPAM
Author-email: gpam@gmail.com
License: Apache-2.0
Project-URL: Documentation, https://gitlab.com/gpam/victor/SERVICES/victor-pecas
Project-URL: Code, https://gitlab.com/gpam/victor/SERVICES/victor-pecas
Project-URL: Issue tracker, https://gitlab.com/victor/SERVICES/victor-pecas/issues
Platform: UNKNOWN
Classifier: Development Status :: 5 - Production/Stable
Classifier: Intended Audience :: Developers
Classifier: License :: OSI Approved :: Apache Software License
Classifier: Operating System :: OS Independent
Classifier: Programming Language :: Python :: 3 :: Only
Classifier: Programming Language :: Python :: 3.6
Classifier: Programming Language :: Python :: 3.7
Classifier: Programming Language :: Python :: 3.8
Classifier: Programming Language :: Python :: 3.9
Classifier: Programming Language :: Python :: Implementation :: CPython
Classifier: Topic :: Software Development :: Libraries
Requires-Python: >=3.6.0
Requires-Dist: nltk (>=3.4.5)
Requires-Dist: numpy (>=1.18.3)
Requires-Dist: scikit-learn (>=0.22.2.post1)
Requires-Dist: xgboost (==1.3.3)
